__init__.py
data.py
generator.py
registration.py
syn.py
syn_utils.py
pysyn-0.0.21.dist-info/DESCRIPTION.rst
pysyn-0.0.21.dist-info/METADATA
pysyn-0.0.21.dist-info/RECORD
pysyn-0.0.21.dist-info/WHEEL
pysyn-0.0.21.dist-info/entry_points.txt
pysyn-0.0.21.dist-info/metadata.json
pysyn-0.0.21.dist-info/top_level.txt
tests/__init__.py
tests/utils.py
web-server/__init__.py
web-server/http-server-base.py
web-server/http-server.py
web-server/webserver.py
