Metadata-Version: 2.0
Name: pysyn
Version: 0.0.21
Summary: Password management and data synchronization app
Home-page: https://0xacab.org/vdegou/Syn
Author: Victor De Gouveia
Author-email: vdegou@gmail.com
License: UNKNOWN
Platform: UNKNOWN
Requires-Dist: Click
Requires-Dist: leap.common
Requires-Dist: leap.soledad
Requires-Dist: pyperclip
Requires-Dist: pysqlcipher
Requires-Dist: pytest
Requires-Dist: tornado
Requires-Dist: zope.proxy
